black_box/__init__.py
black_box/blackbox.py
black_box-1.0.2.dist-info/LICENSE
black_box-1.0.2.dist-info/METADATA
black_box-1.0.2.dist-info/WHEEL
black_box-1.0.2.dist-info/top_level.txt
black_box-1.0.2.dist-info/RECORD
