Metadata-Version: 2.1
Name: black-box
Version: 1.0.2
Summary: A Python module for parallel optimization of expensive black-box functions
Home-page: https://github.com/paulknysh/blackbox
Author: Paul Knysh
Author-email: paul.knysh@gmail.com
License: UNKNOWN
Platform: UNKNOWN
Classifier: Programming Language :: Python :: 3
Classifier: License :: OSI Approved :: MIT License
Classifier: Operating System :: OS Independent
Requires-Python: >=3.6
Requires-Dist: numpy
Requires-Dist: scipy
